fanficfare/HtmlTagStack.py
fanficfare/__init__.py
fanficfare/cli.py
fanficfare/configurable.py
fanficfare/dateutils.py
fanficfare/defaults.ini
fanficfare/epubutils.py
fanficfare/example.ini
fanficfare/exceptions.py
fanficfare/geturls.py
fanficfare/htmlcleanup.py
fanficfare/htmlheuristics.py
fanficfare/mobi.py
fanficfare/mobihtml.py
fanficfare/requestable.py
fanficfare/six.py
fanficfare/story.py
fanficfare/translit.py
fanficfare/adapters/__init__.py
fanficfare/adapters/adapter_adastrafanficcom.py
fanficfare/adapters/adapter_adultfanfictionorg.py
fanficfare/adapters/adapter_alternatehistorycom.py
fanficfare/adapters/adapter_althistorycom.py
fanficfare/adapters/adapter_archiveofourownorg.py
fanficfare/adapters/adapter_asexstoriescom.py
fanficfare/adapters/adapter_ashwindersycophanthexcom.py
fanficfare/adapters/adapter_asianfanficscom.py
fanficfare/adapters/adapter_bdsmlibrarycom.py
fanficfare/adapters/adapter_bloodshedversecom.py
fanficfare/adapters/adapter_cfaa.py
fanficfare/adapters/adapter_chaossycophanthexcom.py
fanficfare/adapters/adapter_chireadscom.py
fanficfare/adapters/adapter_chosentwofanficcom.py
fanficfare/adapters/adapter_darksolaceorg.py
fanficfare/adapters/adapter_deviantartcom.py
fanficfare/adapters/adapter_dokugacom.py
fanficfare/adapters/adapter_dracoandginnycom.py
fanficfare/adapters/adapter_efpfanficnet.py
fanficfare/adapters/adapter_erosnsapphosycophanthexcom.py
fanficfare/adapters/adapter_fanficauthorsnet.py
fanficfare/adapters/adapter_fanficsme.py
fanficfare/adapters/adapter_fanfictalkcom.py
fanficfare/adapters/adapter_fanfictionnet.py
fanficfare/adapters/adapter_fanfictionsfr.py
fanficfare/adapters/adapter_fanfiktionde.py
fanficfare/adapters/adapter_ficbooknet.py
fanficfare/adapters/adapter_fictionalleyarchiveorg.py
fanficfare/adapters/adapter_fictionhuntcom.py
fanficfare/adapters/adapter_fictionlive.py
fanficfare/adapters/adapter_fictionmaniatv.py
fanficfare/adapters/adapter_fictionpresscom.py
fanficfare/adapters/adapter_ficwadcom.py
fanficfare-4.54.0.dist-info/licenses/LICENSE
fanficfare-4.54.0.dist-info/METADATA
fanficfare-4.54.0.dist-info/WHEEL
fanficfare-4.54.0.dist-info/entry_points.txt
fanficfare-4.54.0.dist-info/top_level.txt
fanficfare-4.54.0.dist-info/RECORD
