Metadata-Version: 2.4
Name: FanFicFare
Version: 4.54.0
Summary: A tool for downloading fanfiction to eBook formats
Author-email: Jim Miller <retiefjimm@gmail.com>
Maintainer-email: Jim Miller <retiefjimm@gmail.com>
License-Expression: Apache-2.0
Project-URL: Homepage, https://github.com/JimmXinu/FanFicFare
Project-URL: Bug Reports, https://github.com/JimmXinu/FanFicFare/issues
Project-URL: Plugin Discussion Thread, https://www.mobileread.com/forums/showthread.php?t=259221
Keywords: fanfiction,download,ebook,epub,html
Classifier: Development Status :: 5 - Production/Stable
Classifier: Environment :: Console
Classifier: Intended Audience :: End Users/Desktop
Classifier: Topic :: Internet :: WWW/HTTP
Classifier: Programming Language :: Python :: 3
Classifier: Programming Language :: Python :: 3.7
Classifier: Programming Language :: Python :: 3.8
Classifier: Programming Language :: Python :: 3.9
Classifier: Programming Language :: Python :: 3.10
Classifier: Programming Language :: Python :: 3.11
Classifier: Programming Language :: Python :: 3 :: Only
Requires-Python: >=3.7
License-File: LICENSE
Requires-Dist: beautifulsoup4
Requires-Dist: chardet
Requires-Dist: html5lib
Requires-Dist: html2text
Requires-Dist: cloudscraper
Requires-Dist: urllib3>=1.26.2
Requires-Dist: requests>=2.25.1
Requires-Dist: requests-file
Requires-Dist: brotli
Requires-Dist: pywin32; platform_system == "Windows"
Provides-Extra: image-processing
Requires-Dist: Pillow>=3.3.0; extra == "image-processing"
Dynamic: license-file
